topsis_102218082_nikhil/__init__.py
topsis_102218082_nikhil/topsis.py
topsis_102218082_nikhil-0.3.dist-info/LICENSE
topsis_102218082_nikhil-0.3.dist-info/METADATA
topsis_102218082_nikhil-0.3.dist-info/WHEEL
topsis_102218082_nikhil-0.3.dist-info/entry_points.txt
topsis_102218082_nikhil-0.3.dist-info/top_level.txt
topsis_102218082_nikhil-0.3.dist-info/RECORD
