Metadata-Version: 2.1
Name: topsis-102218082-nikhil
Version: 0.3
Summary: A Python package for TOPSIS method
Author: Nikhil Gupta
Author-email: nikhilgupta8235@gmail.com
Classifier: Programming Language :: Python :: 3
Classifier: License :: OSI Approved :: MIT License
Classifier: Operating System :: OS Independent
Requires-Python: >=3.6
License-File: LICENSE
Requires-Dist: numpy
Requires-Dist: pandas
